{"weather":[{"level":"1","type":"weather","question":"Ma langen taevast ja te võite minus mängida, aga te peate end kimbutama! Mis ma olen?","hints":[{"text":"️ Mul on külm."},{"text":"Minuga saab teha lumepalle."},{"text":"️ Olen valge."}],"options":[{"label":"Vihm","isCorrect":false},{"label":"Lumi","isCorrect":true},{"label":"Päikesepaiste","isCorrect":false}],"additionalData":{"backgroundColor":"0xFF9370DB","category":"weather","icon":"🌍"}},{"level":"2","type":"weather","question":"Tulen taevast alla ja teen kõik märjaks. Sa vajad vihmavarju! Mis ma olen?","hints":[{"text":"Kukun pilvedest."},{"text":"Võin täita lompe."},{"text":"️ Taimed vajavad mind kasvamiseks."}],"options":[{"label":"Vihm","isCorrect":true},{"label":"Tuul","isCorrect":false},{"label":"Lumi","isCorrect":false}],"additionalData":{"backgroundColor":"0xFF9370DB","category":"weather","icon":"🌍"}},{"level":"3","type":"weather","question":"Olen suur ja särav ning annan sulle soojust ja valgust. Mis ma olen?","hints":[{"text":"☀️ Olen päeval taevas."},{"text":"Sul on vaja päikeseprille, kui ma väljas olen."},{"text":"Ma olen väga kuum."}],"options":[{"label":"Kuu","isCorrect":false},{"label":"Päike","isCorrect":true},{"label":"Täht","isCorrect":false}],"additionalData":{"backgroundColor":"0xFF9370DB","category":"weather","icon":"🌍"}},{"level":"4","type":"weather","question":"Lehti liigutan puudel. Vahel olen õrn, vahel tugev. Mis ma olen?","hints":[{"text":"Olen õhk, mis liigub."},{"text":"Ma võin su mütsi maha puhuda."},{"text":"️ Minuga saab lennata lohega."}],"options":[{"label":"Tuul","isCorrect":true},{"label":"Tuli","isCorrect":false},{"label":"Vesi","isCorrect":false}],"additionalData":{"backgroundColor":"0xFF9370DB","category":"weather","icon":"🌍"}},{"level":"5","type":"weather","question":"Olen valge ja kohev ning hõljun taevas. Vahel toon vihma! Mis ma olen?","hints":[{"text":"Näen välja nagu lambad."},{"text":"️ Lennukid lendavad minust läbi."},{"text":"Saan vihmaga hakkama."}],"options":[{"label":"Pilv","isCorrect":true},{"label":"Täht","isCorrect":false},{"label":"Mägi","isCorrect":false}],"additionalData":{"backgroundColor":"0xFF9370DB","category":"weather","icon":"🌍"}},{"level":"6","type":"weather","question":"Olen suur torm, kus on palju tuult ja vihma. Vahel on äikest ja välku! Mis ma olen?","hints":[{"text":"Ma olen hirmus."},{"text":"️ Sa peaksid sees olema, kui ma tulen."},{"text":"Teen valju häält."}],"options":[{"label":"Lumehelbeke","isCorrect":false},{"label":"Äike","isCorrect":true},{"label":"Vikerkaar","isCorrect":false}],"additionalData":{"backgroundColor":"0xFF9370DB","category":"weather","icon":"🌍"}},{"level":"7","type":"weather","question":"Olen värviline kaar taevas, mida on näha pärast vihma. Mis ma olen?","hints":[{"text":"Mul on palju värve."},{"text":"Sa näed mind, kui päike paistab pärast vihma."},{"text":"Ma olen ilus."}],"options":[{"label":"Tornado","isCorrect":false},{"label":"Vikerkaar","isCorrect":true},{"label":"Hail","isCorrect":false}],"additionalData":{"backgroundColor":"0xFF9370DB","category":"weather","icon":"🌍"}},{"level":"8","type":"weather","question":"Ma olen tillukesed jäägraanulid, mis taevast langevad. Ma võin põrgata, kui ma vastu maad löön! Mis ma olen?","hints":[{"text":"Olen jääst tehtud."},{"text":"Võin põrgata"},{"text":"️ Olen nagu külmunud vihm."}],"options":[{"label":"Vihm","isCorrect":false},{"label":"Hail","isCorrect":true},{"label":"Udu","isCorrect":false}],"additionalData":{"backgroundColor":"0xFF9370DB","category":"weather","icon":"🌍"}},{"level":"9","type":"weather","question":"Mul on väga palav ilm, kus pole pikka aega vihma, kuivatan taimi ja maad. Mis ma olen?","hints":[{"text":"Ma olen väga kuum."},{"text":"Taimedele ma ei meeldi!"},{"text":"️ Juhtun kõrbes palju"}],"options":[{"label":"Üleujutus","isCorrect":false},{"label":"Põud","isCorrect":true},{"label":"Blizzard","isCorrect":false}],"additionalData":{"backgroundColor":"0xFF9370DB","category":"weather","icon":"🌍"}},{"level":"10","type":"weather","question":"Olen pöörlev õhusammas. Olen vägivaldne keerlev tuul, mis võib hävitada kõik minu teel oleva! Mis ma olen?","hints":[{"text":"️ Olen väga ohtlik tuuleliik."},{"text":"Peaksid minu eest keldris peavarju võtma."},{"text":"Näen välja nagu lehter."}],"options":[{"label":"Orkaan","isCorrect":false},{"label":"Tornado","isCorrect":true},{"label":"Monsoon","isCorrect":false}],"additionalData":{"backgroundColor":"0xFF9370DB","category":"weather","icon":"🌍"}}],"ocean":[{"level":"1","type":"ocean","question":"Olen suur ja sinine ning paadid seilavad minu peal. Mis ma olen?","hints":[{"text":"Olen väga-väga suur."},{"text":"Paadid hõljuvad minu peal."},{"text":"Palju loomi elab minus."}],"options":[{"label":"Jõgi","isCorrect":false},{"label":"Ookean","isCorrect":true},{"label":"Järv","isCorrect":false}],"additionalData":{"backgroundColor":"0xFF9370DB","category":"ocean","icon":"🌍"}},{"level":"2","type":"ocean","question":"Mul on kest ja liigun ookeanipõhjas väga aeglaselt. Kes ma olen?","hints":[{"text":"Olen aeglane liikuja."},{"text":"Kannan oma maja selili."},{"text":"Vahel süüakse mind salatites."}],"options":[{"label":"Tähtkuju","isCorrect":false},{"label":"Merikilpkonn","isCorrect":false},{"label":"Tigu","isCorrect":true}],"additionalData":{"backgroundColor":"0xFF9370DB","category":"ocean","icon":"🌍"}},{"level":"3","type":"ocean","question":"Ujun ookeanis ja mul on kaheksa kätt. Kes ma olen?","hints":[{"text":"Mul on palju relvi, mis mind aitavad."},{"text":"Mõned söövad mind grillitult."},{"text":"Ma võin tinti pritsida!"}],"options":[{"label":"Kaheksajalg","isCorrect":true},{"label":"Delfiin","isCorrect":false},{"label":"Krabi","isCorrect":false}],"additionalData":{"backgroundColor":"0xFF9370DB","category":"ocean","icon":"🌍"}},{"level":"4","type":"ocean","question":"Olen väga suur teravate hammastega kala. Mõned inimesed kardavad mind! Mis ma olen?","hints":[{"text":"Olen kiskja."},{"text":"Mul on ridasid ja ridasid hambaid."},{"text":"Inimesed näevad tihti, kuidas mu uim läbi vee lõikab."}],"options":[{"label":"Kuldkala","isCorrect":false},{"label":"Haid","isCorrect":true},{"label":"Vaal","isCorrect":false}],"additionalData":{"backgroundColor":"0xFF9370DB","category":"ocean","icon":"🌍"}},{"level":"5","type":"ocean","question":"Olen imetaja, kes elab ookeanis ja teeb klõbisevat häält. Mis ma olen?","hints":[{"text":"Olen väga sõbralik ja mänguhimuline."},{"text":"️ Kasutan kajalokatsiooni oma toidu leidmiseks."},{"text":"Hüppan veest välja."}],"options":[{"label":"Tihend","isCorrect":false},{"label":"Delfiin","isCorrect":true},{"label":"Morss","isCorrect":false}],"additionalData":{"backgroundColor":"0xFF9370DB","category":"ocean","icon":"🌍"}},{"level":"6","type":"ocean","question":"Olen värvikas kodu ookeanis, mida ehivad pisikesed loomad. Mis ma olen?","hints":[{"text":"Paljud kalad elavad minu lähedal."},{"text":"Olen tehtud väikestest luukeredest."},{"text":"☀️ Olen suremas, sest ookean läheb liiga soojaks"}],"options":[{"label":"Laevahukk","isCorrect":false},{"label":"Korallriff","isCorrect":true},{"label":"Kelbimets","isCorrect":false}],"additionalData":{"backgroundColor":"0xFF9370DB","category":"ocean","icon":"🌍"}},{"level":"7","type":"ocean","question":"Olen hiiglaslik mereolend, maakera suurim loom, kes laulab üksildast laulu. Mis ma olen?","hints":[{"text":"Olen vaala tüüp."},{"text":"Minu laul on väga sügav."},{"text":"Toitun peamiselt pisikestest krevetilaadsetest olenditest."}],"options":[{"label":"Suurepärane valge hai","isCorrect":false},{"label":"Sinivaal","isCorrect":true},{"label":"Hiiglaslik kalmaar","isCorrect":false}],"additionalData":{"backgroundColor":"0xFF9370DB","category":"ocean","icon":"🌍"}},{"level":"8","type":"ocean","question":"Olen tasane kala, mis sulandub kokku ookeanipõhjaga. Mul on mõlemad silmad ühel pool keha! Mis ma olen?","hints":[{"text":"️ Minu silmad on natuke ebatavalised."},{"text":"Mind võib olla raske märgata."},{"text":"Minu kuju on nagu praetud hommikusöögil."}],"options":[{"label":"Merikurk","isCorrect":false},{"label":"Meduusi","isCorrect":false},{"label":"Lest","isCorrect":true}],"additionalData":{"backgroundColor":"0xFF9370DB","category":"ocean","icon":"🌍"}},{"level":"9","type":"ocean","question":"Olen tõusude ja maakera keerlemisest tekkinud tugeva, keerleva veealuse voolu tüüp, mõnikord väldivad laevad mind. Mis ma olen?","hints":[{"text":"Keerlen ringi."},{"text":"Olen väga võimas vool."},{"text":"️ Olen ka ilmanähtus, mis võib juhtuda maal"}],"options":[{"label":"Ripi tõus","isCorrect":false},{"label":"Tsunami","isCorrect":false},{"label":"Mullivann","isCorrect":true}],"additionalData":{"backgroundColor":"0xFF9370DB","category":"ocean","icon":"🌍"}},{"level":"10","type":"ocean","question":"Olen koht ookeanis, kus on väga-väga pime ja elavad imelikud olendid, kelle kehal on tuled. Mis ma olen?","hints":[{"text":"Alati on öö, kus ma olen."},{"text":"Minus helendavad mõned kalad."},{"text":"Olen mere põhjas."}],"options":[{"label":"Päikeselised madalikud","isCorrect":false},{"label":"Kesköö tsoon","isCorrect":true},{"label":"Madal riff","isCorrect":false}],"additionalData":{"backgroundColor":"0xFF9370DB","category":"ocean","icon":"🌍"}}]}