{"animal":[{"level":"1","type":"animal","question":"Ma lähen \"Meow\"! Mis ma olen?","hints":[{"text":"Mulle meeldib juua piima."},{"text":"Mulle meeldib lõngaga mängida."},{"text":"nurrun siis, kui olen õnnelik."}],"options":[{"label":"Koer","isCorrect":false},{"label":"Kass","isCorrect":true},{"label":"Linnuke","isCorrect":false}],"additionalData":{"backgroundColor":"0xFF9370DB","category":"animal","icon":"🐾"}},{"level":"2","type":"animal","question":"Ma ütlen \"Vooder! Woof!\" ja liputa mu saba. Mis ma olen?","hints":[{"text":"Mulle meeldib luid närida."},{"text":"Mulle meeldib fetchi mängida."},{"text":"Kaitsen teie maja."}],"options":[{"label":"Koer","isCorrect":true},{"label":"Lehm","isCorrect":false},{"label":"Siga","isCorrect":false}],"additionalData":{"backgroundColor":"0xFF9370DB","category":"animal","icon":"🐾"}},{"level":"3","type":"animal","question":"Ma ütlen \"Moo!\". ja anna piima. Mis ma olen?","hints":[{"text":"Söön rohtu."},{"text":"Olen mustvalge."},{"text":"Elan talus."}],"options":[{"label":"Pardike","isCorrect":false},{"label":"Lehm","isCorrect":true},{"label":"Hobune","isCorrect":false}],"additionalData":{"backgroundColor":"0xFF9370DB","category":"animal","icon":"🐾"}},{"level":"4","type":"animal","question":"Ma ütlen \"Quack! Quack!\" ja uju tiigis. Mis ma olen?","hints":[{"text":"Mul on suled."},{"text":"Minu nokk on oranž."},{"text":"Mulle meeldib ujuda."}],"options":[{"label":"Pardike","isCorrect":true},{"label":"Kala","isCorrect":false},{"label":"Konn","isCorrect":false}],"additionalData":{"backgroundColor":"0xFF9370DB","category":"animal","icon":"🐾"}},{"level":"5","type":"animal","question":"Ma lähen \"Olgu! Oink!\" ja meeldib mudas veereda. Mis ma olen?","hints":[{"text":"Mul on nuhtlus."},{"text":"Olen roosa."},{"text":"Elan talus."}],"options":[{"label":"Siga","isCorrect":true},{"label":"Lambad","isCorrect":false},{"label":"Kana","isCorrect":false}],"additionalData":{"backgroundColor":"0xFF9370DB","category":"animal","icon":"🐾"}},{"level":"6","type":"animal","question":"Ma ütlen \"Naaber!\". ja sa võid minu peal sõita. Mis ma olen?","hints":[{"text":"Mul on pikk lakk."},{"text":"Mulle meeldib porgandeid süüa."},{"text":"Inimesed sõidavad minuga."}],"options":[{"label":"Hobune","isCorrect":true},{"label":"Eesel","isCorrect":false},{"label":"Kitseke","isCorrect":false}],"additionalData":{"backgroundColor":"0xFF9370DB","category":"animal","icon":"🐾"}},{"level":"7","type":"animal","question":"Ma hüppan ringi ja mul on suured kõrvad. Mis ma olen?","hints":[{"text":"Mulle meeldib porgandeid süüa."},{"text":"Mul on kohev saba."},{"text":"Mulle meeldib rohtu süüa."}],"options":[{"label":"Jänes","isCorrect":true},{"label":"Orav","isCorrect":false},{"label":"Hiir","isCorrect":false}],"additionalData":{"backgroundColor":"0xFF9370DB","category":"animal","icon":"🐾"}},{"level":"8","type":"animal","question":"Mul on pikk pakiruum ja suured kõrvad. Mis ma olen?","hints":[{"text":"Mulle meeldib süüa maapähkleid."},{"text":"Olen väga suur."},{"text":"Elan Aafrikas ja Aasias."}],"options":[{"label":"Elevant","isCorrect":true},{"label":"Rhino","isCorrect":false},{"label":"Hippo","isCorrect":false}],"additionalData":{"backgroundColor":"0xFF9370DB","category":"animal","icon":"🐾"}},{"level":"9","type":"animal","question":"Ma möirgan väga valjult ja olen džungli kuningas. Mis ma olen?","hints":[{"text":"Mul on suur lakk."},{"text":"Söön liha."},{"text":"Inimesed kutsuvad mind kuningaks."}],"options":[{"label":"Lõvi","isCorrect":true},{"label":"Tiiger","isCorrect":false},{"label":"Karu","isCorrect":false}],"additionalData":{"backgroundColor":"0xFF9370DB","category":"animal","icon":"🐾"}},{"level":"10","type":"animal","question":"Ma olen roheline ja hop. Mulle meeldib kärbseid süüa. Mis ma olen?","hints":[{"text":"Elan vee lähedal."},{"text":"Mul on pikk kleepuv keel."},{"text":"Püüan keelega lutikaid."}],"options":[{"label":"Konn","isCorrect":true},{"label":"Sisalik","isCorrect":false},{"label":"Kilpkond","isCorrect":false}],"additionalData":{"backgroundColor":"0xFF9370DB","category":"animal","icon":"🐾"}}],"weather":[{"level":"1","type":"weather","question":"Kukun taevast alla ja teen kõik märjaks. Mis ma olen?","hints":[{"text":"Olen pärit pilvedest"},{"text":"Sa vajad vihmavarju, kui ma siin olen"},{"text":"️ Aitan taimedel kasvada"}],"options":[{"label":"Päike","isCorrect":false},{"label":"Vihm","isCorrect":true},{"label":"Tuul","isCorrect":false}],"additionalData":{"backgroundColor":"0xFF87CEEB","category":"weather","icon":"🌦️"}},{"level":"2","type":"weather","question":"Olen kuum ja särav ning säran taevas. Mis ma olen?","hints":[{"text":"Olen kollane"},{"text":"Sul on vaja päikeseprille, kui ma olen väljas"},{"text":"↑ Annan teile soojust"}],"options":[{"label":"Kuu","isCorrect":false},{"label":"Päike","isCorrect":true},{"label":"Täht","isCorrect":false}],"additionalData":{"backgroundColor":"0xFFFFD700","category":"weather","icon":"☀️"}},{"level":"3","type":"weather","question":"Puhun lehed ja panen puud tantsima. Mis ma olen?","hints":[{"text":"Võin olla tugev või õrn"},{"text":"Minuga saab lohet lennutada"},{"text":"Mul ei ole värvi"}],"options":[{"label":"Vihm","isCorrect":false},{"label":"Tuul","isCorrect":true},{"label":"Lumi","isCorrect":false}],"additionalData":{"backgroundColor":"0xFFA9A9A9","category":"weather","icon":"🌬️"}},{"level":"4","type":"weather","question":"Olen külm ja valge ning langen talvel taevast alla. Mis ma olen?","hints":[{"text":"️ Olen valmistatud veest, kuid külmutatud"},{"text":"️ Minuga saab teha lumememme"},{"text":"Sa kannad kindaid, kui ma ümber olen"}],"options":[{"label":"Lumi","isCorrect":true},{"label":"Udu","isCorrect":false},{"label":"Hail","isCorrect":false}],"additionalData":{"backgroundColor":"0xFFFFFFFF","category":"weather","icon":"🌨️"}},{"level":"5","type":"weather","question":"Olen hall ja katan päikese. Mis ma olen?","hints":[{"text":"️ Olen kõrgel taevas"},{"text":"Saan õues tumedamaks muuta"},{"text":"Näen vahel välja nagu kohevad lambad"}],"options":[{"label":"Pilv","isCorrect":true},{"label":"Täht","isCorrect":false},{"label":"Vikerkaar","isCorrect":false}],"additionalData":{"backgroundColor":"0xFFD3D3D3","category":"weather","icon":"☁️"}},{"level":"6","type":"weather","question":"Tulen peale vihma ja mul on palju värve. Mis ma olen?","hints":[{"text":"Mul on punane, kollane ja sinine"},{"text":"Sa näed mind ainult siis, kui päike on väljas"},{"text":"▫ Ma näen välja nagu värviline kaar"}],"options":[{"label":"Pikne","isCorrect":false},{"label":"Vikerkaar","isCorrect":true},{"label":"Loik","isCorrect":false}],"additionalData":{"backgroundColor":"0xFFE6E6FA","category":"weather","icon":"🌈"}},{"level":"7","type":"weather","question":"Olen väga vali ja välgutan tormi ajal taevas. Mis ma olen?","hints":[{"text":"Tulen äikesega"},{"text":"▫️ Ma võin olla ohtlik"},{"text":"Olen särav ja äkiline"}],"options":[{"label":"Pikne","isCorrect":true},{"label":"Hail","isCorrect":false},{"label":"Tuul","isCorrect":false}],"additionalData":{"backgroundColor":"0xFF4B0082","category":"weather","icon":"⚡"}},{"level":"8","type":"weather","question":"Olen vali heli, mis tuleb peale välku. Mis ma olen?","hints":[{"text":"Ma kolin ja poom"},{"text":"️ Juhtun tormide ajal"},{"text":"Sa kuuled mind kaugel"}],"options":[{"label":"Äike","isCorrect":true},{"label":"Vihm","isCorrect":false},{"label":"Tuul","isCorrect":false}],"additionalData":{"backgroundColor":"0xFF708090","category":"weather","icon":"⛈️"}},{"level":"9","type":"weather","question":"Olen väikesed jääpallid, mis langevad taevast. Mis ma olen?","hints":[{"text":"Olen külmunud vihm"},{"text":"Ouch! Ma võin haiget teha, kui ma sind löön!"},{"text":"Ma olen nagu väikesed jääpallid."}],"options":[{"label":"Lumi","isCorrect":false},{"label":"Sleet","isCorrect":false},{"label":"Hail","isCorrect":true}],"additionalData":{"backgroundColor":"0xFFA0A0A0","category":"weather","icon":"🌨️"}},{"level":"10","type":"weather","question":"Olen külm ja märg, segu vihmast ja lumest. Mis ma olen?","hints":[{"text":"Ma ei ole päris vihm, mitte päris lumi"},{"text":"️ Olen libe"},{"text":"️ Kukun siis, kui see on lihtsalt külmumise ümber"}],"options":[{"label":"Sleet","isCorrect":true},{"label":"Lumi","isCorrect":false},{"label":"Hail","isCorrect":false}],"additionalData":{"backgroundColor":"0xFFD8BFD8","category":"weather","icon":"🌧️"}}]}