{"cosmos":[{"level":"1","type":"cosmos","question":"Olen suur ja särav ning tulen öösel välja. Twinkin kõrgel, mis ma olen?","hints":[{"text":"Mul on palju, palju sõpru taevas."},{"text":"Sa näed mind ainult siis, kui on pime."},{"text":"▫ Ma säran väga kaugel"}],"options":[{"label":"Kuu","isCorrect":false},{"label":"Täht","isCorrect":true},{"label":"Pilv","isCorrect":false}],"additionalData":{"backgroundColor":"0xFF9370DB","category":"cosmos","icon":"🌍"}},{"level":"2","type":"cosmos","question":"Olen suur ja ümmargune ning annan päeva jooksul valgust. Mis ma olen?","hints":[{"text":"Ma olen väga-väga kuum."},{"text":"Aitan taimedel kasvada."},{"text":"Kadun öösel."}],"options":[{"label":"Kuu","isCorrect":false},{"label":"Päike","isCorrect":true},{"label":"Planeet","isCorrect":false}],"additionalData":{"backgroundColor":"0xFF9370DB","category":"cosmos","icon":"🌍"}},{"level":"3","type":"cosmos","question":"Ma käin Maa peal ringi, aga ma ei ole lennuk. Mis ma olen?","hints":[{"text":"Vahel olen ring, vahel ka liumägi."},{"text":"Libahundid uluvad minu peale."},{"text":"Inimesed ütlevad vahel, et ma olen valmistatud juustust"}],"options":[{"label":"Kuu","isCorrect":true},{"label":"Rocket","isCorrect":false},{"label":"Linnuke","isCorrect":false}],"additionalData":{"backgroundColor":"0xFF9370DB","category":"cosmos","icon":"🌍"}},{"level":"4","type":"cosmos","question":"Olen hiiglaslik gaasipall, mis paistab väga eredalt, nagu meie päike, aga kaugel. Mis ma olen?","hints":[{"text":"Ma olen Maast väga kaugel."},{"text":"Teen ise valguse"},{"text":"↑ Mind on taevas palju."}],"options":[{"label":"Planeet","isCorrect":false},{"label":"Täht","isCorrect":true},{"label":"Kuu","isCorrect":false}],"additionalData":{"backgroundColor":"0xFF9370DB","category":"cosmos","icon":"🌍"}},{"level":"5","type":"cosmos","question":"Olen suur ja ümmargune ning keerutan ümber Päikese. Sa elad minu peal! Mis ma olen?","hints":[{"text":"See on sinu kodu."},{"text":"Mul on palju vett."},{"text":"Inimesed elavad minu peal"}],"options":[{"label":"Marss","isCorrect":false},{"label":"Maa","isCorrect":true},{"label":"Jupiter","isCorrect":false}],"additionalData":{"backgroundColor":"0xFF9370DB","category":"cosmos","icon":"🌍"}},{"level":"6","type":"cosmos","question":"Ma olen kujund, mida näeb tähtedest koosnevas öötaevas. Mis ma olen?","hints":[{"text":"Ühte nimetatakse Suureks Karuks"},{"text":"▫ Valmistatud paljudest tähtedest"},{"text":"See ei ole üks täht üksi."}],"options":[{"label":"Planeet","isCorrect":false},{"label":"Konstellatsioon","isCorrect":true},{"label":"Meteoor","isCorrect":false}],"additionalData":{"backgroundColor":"0xFF9370DB","category":"cosmos","icon":"🌍"}},{"level":"7","type":"cosmos","question":"Olen väike, kivine või metalne objekt, mis tiirleb ümber Päikese, väiksem kui planeet. Mis ma olen?","hints":[{"text":"️ Ma ei ole täht ega planeet"},{"text":"Ma olen väiksem kui Maa."},{"text":"Paljud meist elavad vöös."}],"options":[{"label":"Asteroid","isCorrect":true},{"label":"Satelliit","isCorrect":false},{"label":"Komeet","isCorrect":false}],"additionalData":{"backgroundColor":"0xFF9370DB","category":"cosmos","icon":"🌍"}},{"level":"8","type":"cosmos","question":"Olen planeet, tuntud kui \"Punane planeet\". Mis ma olen?","hints":[{"text":"▫ Inimesed tahavad mind külastada!"},{"text":"Minu värv tuleb roostest."},{"text":"Mõned arvavad, et siin elavad tulnukad."}],"options":[{"label":"Veenus","isCorrect":false},{"label":"Marss","isCorrect":true},{"label":"Saturn","isCorrect":false}],"additionalData":{"backgroundColor":"0xFF9370DB","category":"cosmos","icon":"🌍"}},{"level":"9","type":"cosmos","question":"Ma olen väga kaugel. Valgusel kulub palju aastaid, et jõuda meieni minu juurest, paljude tähtede grupist. Mis ma olen?","hints":[{"text":"Ma olen nagu suur tähtede linn."},{"text":"Võin olla spiraalikujuline."},{"text":"Meie päike on osa minust."}],"options":[{"label":"Asteroid","isCorrect":false},{"label":"Galaxy","isCorrect":true},{"label":"Nebula","isCorrect":false}],"additionalData":{"backgroundColor":"0xFF9370DB","category":"cosmos","icon":"🌍"}},{"level":"10","type":"cosmos","question":"Olen suur jää- ja tolmupall, mis lendab ümber Päikese ja on sabaga, kui lähedale jõuan! Mis ma olen?","hints":[{"text":"️ Olen \"räpane lumepall\"."},{"text":"Olen enamasti külmunud."},{"text":"▫ Maalt näed mind mõnikord teleskoobiga."}],"options":[{"label":"Planeet","isCorrect":false},{"label":"Komeet","isCorrect":true},{"label":"Täht","isCorrect":false}],"additionalData":{"backgroundColor":"0xFF9370DB","category":"cosmos","icon":"🌍"}}],"bug":[{"level":"1","type":"bug","question":"Mul on laigud ja võin lennata. Mis ma olen?","hints":[{"text":"Olen tihti punane."},{"text":"Elan aias"},{"text":"Mul on palju väikseid täppe."}],"options":[{"label":"Liblikas","isCorrect":false},{"label":"Lepatriinu","isCorrect":true},{"label":"Sipelgas","isCorrect":false}],"additionalData":{"backgroundColor":"0xFF8BC34A","category":"bug","icon":"🐛"}},{"level":"2","type":"bug","question":"Ma teen mett. Mis ma olen?","hints":[{"text":"Mulle meeldib lilli külastada."},{"text":"Teen sumisevat häält."},{"text":"Inimestele meeldib süüa seda, mida ma teen."}],"options":[{"label":"Mesilane","isCorrect":true},{"label":"Ämblik","isCorrect":false},{"label":"Uss","isCorrect":false}],"additionalData":{"backgroundColor":"0xFFFDD835","category":"bug","icon":"🐛"}},{"level":"3","type":"bug","question":"Rooman maas ja kannan toitu. Mis ma olen?","hints":[{"text":"Elan koloonias"},{"text":"Olen väga väike."},{"text":"Ma võin kanda endast palju suuremaid asju."}],"options":[{"label":"Tigu","isCorrect":false},{"label":"Sipelgas","isCorrect":true},{"label":"Fly","isCorrect":false}],"additionalData":{"backgroundColor":"0xFF795548","category":"bug","icon":"🐛"}},{"level":"4","type":"bug","question":"Klapin oma värvilisi tiibu ja lendan ringi. Mis ma olen?","hints":[{"text":"Alustan röövikuna."},{"text":"Armastan maanduda lilledele."},{"text":"Mul on ilusad mustrid."}],"options":[{"label":"Liblikas","isCorrect":true},{"label":"Rohutirts","isCorrect":false},{"label":"Põrnikas","isCorrect":false}],"additionalData":{"backgroundColor":"0xFFE91E63","category":"bug","icon":"🐛"}},{"level":"5","type":"bug","question":"Hüppan ja hüppan rohu sisse ja teen 'Chirp Chirp' häält. Mis ma olen?","hints":[{"text":"Olen tihti roheline."},{"text":"Söön taimi."},{"text":"Ma olen väga osav hüppamises."}],"options":[{"label":"Caterpillar","isCorrect":false},{"label":"Rohutirts","isCorrect":true},{"label":"Ämblik","isCorrect":false}],"additionalData":{"backgroundColor":"0xFF607D8B","category":"bug","icon":"🐛"}},{"level":"6","type":"bug","question":"Ehitan võrke, et oma õhtusööki püüda. Mis ma olen?","hints":[{"text":"️ Minu kodu on tehtud kleepuvatest niitidest."},{"text":"️ Mul on kaheksa jalga."},{"text":"Püüan lendavaid putukaid."}],"options":[{"label":"Ämblik","isCorrect":true},{"label":"Mesilane","isCorrect":false},{"label":"Sipelgas","isCorrect":false}],"additionalData":{"backgroundColor":"0xFF9E9E9E","category":"bug","icon":"🐛"}},{"level":"7","type":"bug","question":"Ma võin oma kumaga öötaeva põlema panna. Mis ma olen?","hints":[{"text":"Mu valgus pärineb mu kehast."},{"text":"Olen kõige nähtavam öösel."},{"text":"▫ Mind leidub sageli metsades."}],"options":[{"label":"Firefly","isCorrect":true},{"label":"Põrnikas","isCorrect":false},{"label":"Uss","isCorrect":false}],"additionalData":{"backgroundColor":"0xFFFFEB3B","category":"bug","icon":"🐛"}},{"level":"8","type":"bug","question":"Teen suvel kõva häält, hõõrudes tiibu kokku. Mis ma olen?","hints":[{"text":"☀️ Sa kuuled mind tihti kuumadel päevadel."},{"text":"Minu heli on nagu sumin või siristamine."},{"text":"Elan puudes."}],"options":[{"label":"Kriket","isCorrect":false},{"label":"Cicada","isCorrect":true},{"label":"Lepatriinu","isCorrect":false}],"additionalData":{"backgroundColor":"0xFF4CAF50","category":"bug","icon":"🐛"}},{"level":"9","type":"bug","question":"Kaevan maasse ja teen väikseid künkaid. Mis ma olen?","hints":[{"text":"Ma ei ole uss, vaid elan maa all."},{"text":"Teen koostööd oma perega."},{"text":"️ Minu kodu on näha mustusest tehtud õues"}],"options":[{"label":"Sipelgas","isCorrect":true},{"label":"Põrnikas","isCorrect":false},{"label":"Fly","isCorrect":false}],"additionalData":{"backgroundColor":"0xFF3E2723","category":"bug","icon":"🐛"}},{"level":"10","type":"bug","question":"Ma söön puitu ja ma elan selle sees rühmades. Mis ma olen?","hints":[{"text":"Ma võin tekitada majadele kahju."},{"text":"Söön ja elan ka puudes."},{"text":"Inimesed võivad mind sipelgate pärast eksitada."}],"options":[{"label":"Termiit","isCorrect":true},{"label":"Ämblik","isCorrect":false},{"label":"Fly","isCorrect":false}],"additionalData":{"backgroundColor":"0xA1887F","category":"bug","icon":"🐛"}}]}