{"transport":[{"level":"1","type":"transport","question":"Ma lähen piiksuma! Mul on rattad ja võtan sulle kohad. Mis ma olen?","hints":[{"text":"Paljudel inimestel on üks."},{"text":"Sa näed mind teel."},{"text":"Sa vajad võtit, et mind käivitada."}],"options":[{"label":"Auto","isCorrect":true},{"label":"Koer","isCorrect":false},{"label":"Puu","isCorrect":false}],"additionalData":{"backgroundColor":"0xFF9370DB","category":"transport","icon":"🚗","transportType":"Car"}},{"level":"2","type":"transport","question":"Ma hõljun vee peal ja kannan inimesi. Mis ma olen?","hints":[{"text":"Olen suur ja võin ookeanile minna."},{"text":"😀️ Vajan ankrut, et paigal püsida."},{"text":"Vahel kasutatakse mind pühadeks!"}],"options":[{"label":"Rong","isCorrect":false},{"label":"Paat","isCorrect":true},{"label":"Linnuke","isCorrect":false}],"additionalData":{"backgroundColor":"0xFF9370DB","category":"transport","icon":"🚢","transportType":"Boat"}},{"level":"3","type":"transport","question":"Lendan taevas ja viin inimesed kaugele. Mis ma olen?","hints":[{"text":"️ Olen suurem kui lind."},{"text":"Maandun lennujaamas."},{"text":"️ Mul on tiivad ja mootor."}],"options":[{"label":"Lennuk","isCorrect":true},{"label":"Buss","isCorrect":false},{"label":"Scooter","isCorrect":false}],"additionalData":{"backgroundColor":"0xFF9370DB","category":"transport","icon":"✈️","transportType":"Airplane"}},{"level":"4","type":"transport","question":"Reisin radadel ja kannan paljusid inimesi. Mis ma olen?","hints":[{"text":"️ Ma lähtun erilisest teest."},{"text":"Peatun jaamades."},{"text":"Choo choo!"}],"options":[{"label":"Jalgratas","isCorrect":false},{"label":"Rong","isCorrect":true},{"label":"Õhupall","isCorrect":false}],"additionalData":{"backgroundColor":"0xFF9370DB","category":"transport","icon":"🚂","transportType":"Train"}},{"level":"5","type":"transport","question":"Olen nagu auto, aga suurem ja kannan palju sõpru kooli kaasa. Mis ma olen?","hints":[{"text":"Tavaliselt olen kollane."},{"text":"Mul on peatumismärk, mis tuleb välja."},{"text":"Ma mahutan endasse palju inimesi"}],"options":[{"label":"Veoauto","isCorrect":false},{"label":"Buss","isCorrect":true},{"label":"Takso","isCorrect":false}],"additionalData":{"backgroundColor":"0xFF9370DB","category":"transport","icon":"🚌","transportType":"Bus"}},{"level":"6","type":"transport","question":"Mul on kaks ratast ja sa pedaal, et ma läheks. Mis ma olen?","hints":[{"text":"Sa pead tasakaalustama, et minuga sõita."},{"text":"Mul on kelluke, mida heliseda."},{"text":"️ Olen pargis ratsutamiseks hea."}],"options":[{"label":"Auto","isCorrect":false},{"label":"Jalgratas","isCorrect":true},{"label":"Sleigh","isCorrect":false}],"additionalData":{"backgroundColor":"0xFF9370DB","category":"transport","icon":"🚲","transportType":"Bicycle"}},{"level":"7","type":"transport","question":"Aitan inimesi, kui nad on haiged või haiget saanud. Mul on sireen. Mis ma olen?","hints":[{"text":"Minu sireen läheb 'wee-ooh, wee-ooh!'"},{"text":"Mul on peal eriline valgus."},{"text":"Viin inimesed haiglasse."}],"options":[{"label":"Tuletõrjeauto","isCorrect":false},{"label":"Kiirabi","isCorrect":true},{"label":"Politseiauto","isCorrect":false}],"additionalData":{"backgroundColor":"0xFF9370DB","category":"transport","icon":"🚑","transportType":"Ambulance"}},{"level":"8","type":"transport","question":"Mul on platvorm ja käepidemed. Sa seisad minu peal ja lükkad jalaga. Mis ma olen?","hints":[{"text":"Mul on hea, kui sa oled väike, et ringi liikuda."},{"text":"Tõukad jalaga, et edasi minna."},{"text":"Mul on palju lõbus sõita kõnniteel."}],"options":[{"label":"Mootorratas","isCorrect":false},{"label":"Scooter","isCorrect":true},{"label":"Traktor","isCorrect":false}],"additionalData":{"backgroundColor":"0xFF9370DB","category":"transport","icon":"🛴","transportType":"Scooter"}},{"level":"9","type":"transport","question":"Aitan tulekahjusid kustutada ja olen punane ja vali. Mis ma olen?","hints":[{"text":"▫ Kasutan vett, et takistada asjade põlemist."},{"text":"Mul on pikk redel peal."},{"text":"Tuletõrjujad ajavad mind."}],"options":[{"label":"Prügiveok","isCorrect":false},{"label":"Tuletõrjeauto","isCorrect":true},{"label":"Tsementmikser","isCorrect":false}],"additionalData":{"backgroundColor":"0xFF9370DB","category":"transport","icon":"🚒","transportType":"Firetruck"}},{"level":"10","type":"transport","question":"Kaevan mustuse sisse ja aitan asju ehitada. Mul on suur kühvel. Mis ma olen?","hints":[{"text":"Olen tavaliselt ehitusplatsil."},{"text":"️ Inimesed kannavad minu ümber kõvu mütse."},{"text":"Mul on suur käsi, mis liigutab mustust."}],"options":[{"label":"Auto","isCorrect":false},{"label":"Kaevaja","isCorrect":true},{"label":"Helikopter","isCorrect":false}],"additionalData":{"backgroundColor":"0xFF9370DB","category":"transport","icon":"🚜","transportType":"Excavator"}}],"cosmos":[{"level":"1","type":"cosmos","question":"Olen suur ja kollane ning säran päeval. Mis ma olen?","hints":[{"text":"Hoian sind soojas."},{"text":"Näen välja nagu suur lill taevas."},{"text":"́ ́ ́Tulen hommikul välja."}],"options":[{"label":"Kuu","isCorrect":false},{"label":"Päike","isCorrect":true},{"label":"Täht","isCorrect":false}],"additionalData":{"backgroundColor":"0xFF9370DB","category":"cosmos","icon":"🪐"}},{"level":"2","type":"cosmos","question":"Olen ümmargune ja vahel võib mind ka öösel näha. Muudan kuju! Mis ma olen?","hints":[{"text":"Mul on faasid, nagu poolkuu või täisring."},{"text":"Libahundid nagu mina."},{"text":"Mõned ütlevad, et ma olen valmistatud juustust."}],"options":[{"label":"Täht","isCorrect":false},{"label":"Kuu","isCorrect":true},{"label":"Päike","isCorrect":false}],"additionalData":{"backgroundColor":"0xFF9370DB","category":"cosmos","icon":"🪐"}},{"level":"3","type":"cosmos","question":"Olen pisike ja tõmblen öösel, kaugel, kaugel. Mis ma olen?","hints":[{"text":"Ma olen väga särav."},{"text":"Elan öötaevas."},{"text":"Sa võid minu peale soovida."}],"options":[{"label":"Täht","isCorrect":true},{"label":"Planeet","isCorrect":false},{"label":"Pilv","isCorrect":false}],"additionalData":{"backgroundColor":"0xFF9370DB","category":"cosmos","icon":"🪐"}},{"level":"4","type":"cosmos","question":"Ma olen suur kivi ja vee pall ja sa elad siin! Mis ma olen?","hints":[{"text":"Sa oled kohe minu peal!"},{"text":"Olen ümmargune."},{"text":"Mul on palju vett."}],"options":[{"label":"Marss","isCorrect":false},{"label":"Maa","isCorrect":true},{"label":"Jupiter","isCorrect":false}],"additionalData":{"backgroundColor":"0xFF9370DB","category":"cosmos","icon":"🪐"}},{"level":"5","type":"cosmos","question":"Käin ümber päikese ja olen punane! Mis ma olen?","hints":[{"text":"Olen saanud nime kommibaari värvi järgi"},{"text":"↑ Mind nimetatakse Punaseks Planeediks."},{"text":"▫ Inimesed tahavad mulle kunagi külla tulla."}],"options":[{"label":"Veenus","isCorrect":false},{"label":"Marss","isCorrect":true},{"label":"Saturn","isCorrect":false}],"additionalData":{"backgroundColor":"0xFF9370DB","category":"cosmos","icon":"🪐"}},{"level":"6","type":"cosmos","question":"Olen staaride grupp, kes teeb pilti! Mis ma olen?","hints":[{"text":"Vahel näen välja nagu karu."},{"text":"Olen muster öötaevas."},{"text":"Inimesed kasutasid mind oma tee leidmiseks."}],"options":[{"label":"Planeet","isCorrect":false},{"label":"Konstellatsioon","isCorrect":true},{"label":"Meteoor","isCorrect":false}],"additionalData":{"backgroundColor":"0xFF9370DB","category":"cosmos","icon":"🪐"}},{"level":"7","type":"cosmos","question":"Olen hiiglaslik gaasipall, suurim planeet! Mul on suur punane laik! Mis ma olen?","hints":[{"text":"️ Minu punane laik on suur torm."},{"text":"Olen päikesest väga kaugel."},{"text":"Olen planeetide kuningas"}],"options":[{"label":"Jupiter","isCorrect":true},{"label":"Veenus","isCorrect":false},{"label":"Neptuun","isCorrect":false}],"additionalData":{"backgroundColor":"0xFF9370DB","category":"cosmos","icon":"🪐"}},{"level":"8","type":"cosmos","question":"Minu ümber on ilusad rõngad, jääst ja kivist tehtud! Mis ma olen?","hints":[{"text":"Minu sõrmused on väga sädelevad."},{"text":"Mind valmistatakse enamasti gaasist."},{"text":"Olen väga kaugel."}],"options":[{"label":"Uraan","isCorrect":false},{"label":"Saturn","isCorrect":true},{"label":"Merkuur","isCorrect":false}],"additionalData":{"backgroundColor":"0xFF9370DB","category":"cosmos","icon":"🪐"}},{"level":"9","type":"cosmos","question":"Olen võttestaar, kosmosest tulev kivi, mis põleb taevas! Mis ma olen?","hints":[{"text":"️ Jätan selja taha särava triibu."},{"text":"Mind nimetatakse ka langevaks täheks"},{"text":"Ma põlen ära, kui õhku sisenen."}],"options":[{"label":"Meteoor","isCorrect":true},{"label":"Planeet","isCorrect":false},{"label":"Galaxy","isCorrect":false}],"additionalData":{"backgroundColor":"0xFF9370DB","category":"cosmos","icon":"🪐"}},{"level":"10","type":"cosmos","question":"Kõik, mida näed, kõik tähed ja planeedid, on osa minust. Mis ma olen?","hints":[{"text":"Olen väga-väga suur."},{"text":"Ma olen miljardite tähtede kogum."},{"text":"Maa kuulub mulle."}],"options":[{"label":"Päikesesüsteem","isCorrect":false},{"label":"Galaxy","isCorrect":true},{"label":"Universum","isCorrect":false}],"additionalData":{"backgroundColor":"0xFF9370DB","category":"cosmos","icon":"🪐"}}]}