{"ocean":[{"level":"1","type":"ocean","question":"Mis ma olen? Ma olen suur ja sinine ja minus ujuvad kalad!","hints":[{"text":"Paadid sõidavad minu peal!"},{"text":"Ka sina võid minus ujuda, kui oskad!"},{"text":"Ma katan suurema osa Maast."}],"options":[{"label":"Pilv","isCorrect":false},{"label":"Ookean","isCorrect":true},{"label":"Puu","isCorrect":false}],"additionalData":{"backgroundColor":"0xFF64B5F6","category":"ocean","icon":"🌊"}},{"level":"2","type":"ocean","question":"Kes ma olen? Mul on karp ja ma rooman aeglaselt liival!","hints":[{"text":"Ma elan ookeani lähedal."},{"text":"Ma võin end oma karbi sisse peita."},{"text":"Mõnikord koguvad inimesed minu karpe rannas"}],"options":[{"label":"Linnu","isCorrect":false},{"label":"Kilpkonn","isCorrect":true},{"label":"Koer","isCorrect":false}],"additionalData":{"backgroundColor":"0xFF81C784","category":"ocean","icon":"🐢"}},{"level":"3","type":"ocean","question":"Mis ma olen? Ma olen värviline triibuline kala ja ma peidan end anemooni sisse!","hints":[{"text":"Minu kodu kaitseb mind"},{"text":"Ma olen oranž ja valge."},{"text":"Nemo on üks minust!"}],"options":[{"label":"Klounkala","isCorrect":true},{"label":"Meritäht","isCorrect":false},{"label":"Meduus","isCorrect":false}],"additionalData":{"backgroundColor":"0xFFFFCA28","category":"ocean","icon":"🐠"}},{"level":"4","type":"ocean","question":"Mis ma olen? Mul on kaheksa kätt ja ma elan ookeanis.","hints":[{"text":"Ma võin muuta värve!"},{"text":"Ma olen väga tark!"},{"text":"Ma pritsin tinti, kui ma kardan"}],"options":[{"label":"Vähk","isCorrect":false},{"label":"kaheksajalg","isCorrect":true},{"label":"Vaal","isCorrect":false}],"additionalData":{"backgroundColor":"0xFFCE93D8","category":"ocean","icon":"🐙"}},{"level":"5","type":"ocean","question":"Mis ma olen? Ma olen väga suur ja laulan ookeanis laule.","hints":[{"text":"Ma olen imetaja"},{"text":"Ma hingan õhku läbi seljas oleva augu."},{"text":"Ma olen suurim loom maa peal"}],"options":[{"label":"Delfiin","isCorrect":false},{"label":"Merilõvi","isCorrect":false},{"label":"Vaal","isCorrect":true}],"additionalData":{"backgroundColor":"0xFF4DB6AC","category":"ocean","icon":"🐳"}},{"level":"6","type":"ocean","question":"Mis ma olen? Ma olen teravikuhammas, mille leiad rannast.","hints":[{"text":"Ma tulen ookeanist."},{"text":"Neid on palju kuju, värvi ja suurust."},{"text":"Mina olen mõne mereolendi kodu."}],"options":[{"label":"Kivi","isCorrect":false},{"label":"Koorik","isCorrect":true},{"label":"Sulg","isCorrect":false}],"additionalData":{"backgroundColor":"0xFFFF8A65","category":"ocean","icon":"🐚"}},{"level":"7","type":"ocean","question":"Kes ma olen? Mul on suured küüned ja ma kõnnin rannas külg ees.","hints":[{"text":"Ma elan liivas."},{"text":"Ma võin sind oma küünistega näpistada!"},{"text":"Ma pendeldan külg ees"}],"options":[{"label":"Meritäht","isCorrect":false},{"label":"Vähk","isCorrect":true},{"label":"Merihobu","isCorrect":false}],"additionalData":{"backgroundColor":"0xFFEF5350","category":"ocean","icon":"🦀"}},{"level":"8","type":"ocean","question":"Mis ma olen? Ma olen pikk, peenike kala, millel on terav nina ja palju teravaid hambaid!","hints":[{"text":"Ma olen kiskja!"},{"text":"Ma elan ookeanis."},{"text":"Inimesed kardavad mind!"}],"options":[{"label":"Mõõkkala","isCorrect":false},{"label":"Hai","isCorrect":true},{"label":"Angerjas","isCorrect":false}],"additionalData":{"backgroundColor":"0xFF7986CB","category":"ocean","icon":"🦈"}},{"level":"9","type":"ocean","question":"Mis ma olen? Ma näen välja nagu täht ja elan ookeani põhjas.","hints":[{"text":"Mul on viis kätt või rohkem!"},{"text":"Ma võin oma käed tagasi kasvatada, kui need maha kukuvad."},{"text":"Patrick Spongebobist on üks meist!"}],"options":[{"label":"Meduus","isCorrect":false},{"label":"Merihobu","isCorrect":false},{"label":"Meritäht","isCorrect":true}],"additionalData":{"backgroundColor":"0xFFF06292","category":"ocean","icon":"🌟"}},{"level":"10","type":"ocean","question":"Mis ma olen? Ma olen pikk ja kõhn ja ujun nagu madu meres!","hints":[{"text":"Mul ei ole uimed!"},{"text":"Ma olen kalaliik."},{"text":"Ma peidan end kivide vahele"}],"options":[{"label":"A uss","isCorrect":false},{"label":"Angerjas","isCorrect":true},{"label":"Merekurk","isCorrect":false}],"additionalData":{"backgroundColor":"0xFFA1887F","category":"ocean","icon":"🐍"}}],"bug":[{"level":"1","type":"bug","question":"Mis ma olen? Mul on kuus jalga ja ma armastan sumiseda lillede ümber!","hints":[{"text":"Ma teen mett."},{"text":"Ma lendan oma tiibadega."},{"text":"Ma pistan mõnikord."}],"options":[{"label":"Ant","isCorrect":false},{"label":"Mesilane","isCorrect":true},{"label":"Ämblik","isCorrect":false}],"additionalData":{"backgroundColor":"0xFF80CBC4","category":"bug","icon":"🐝"}},{"level":"2","type":"bug","question":"Mis ma olen? Ma marssin rivis ja kannan suuri murenemisi!","hints":[{"text":"Ma elan koloonias."},{"text":"Ma olen väga väike, kuid tugev."},{"text":"Mind võib leida köögis, kui sa toitu tilgutad."}],"options":[{"label":"Worm","isCorrect":false},{"label":"Ant","isCorrect":true},{"label":"Kärbes","isCorrect":false}],"additionalData":{"backgroundColor":"0xFFE57373","category":"bug","icon":"🐜"}},{"level":"3","type":"bug","question":"Mis ma olen? Ma hüppan ringi ja mulle meeldib aias taimi süüa.","hints":[{"text":"Ma olen sageli roheline."},{"text":"Ma oskan väga kõrgele hüpata."},{"text":"Ma teen siristavat häält."}],"options":[{"label":"Rohutirts","isCorrect":true},{"label":"Ladybug","isCorrect":false},{"label":"Roomik","isCorrect":false}],"additionalData":{"backgroundColor":"0xFFAED581","category":"bug","icon":"🦗"}},{"level":"4","type":"bug","question":"Mis ma olen? Ma olen mustade laikudega punane ja inimesed ütlevad, et ma tooksin õnne!","hints":[{"text":"Ma olen ümmargune."},{"text":"Mul on tiivad, aga ma ei ole lind."},{"text":"Ma söön täisid."}],"options":[{"label":"Liblikas","isCorrect":false},{"label":"Ladybug","isCorrect":true},{"label":"Mardikas","isCorrect":false}],"additionalData":{"backgroundColor":"0xFFEF5350","category":"bug","icon":"🐞"}},{"level":"5","type":"bug","question":"Mis ma olen? Ma hõljun taevas värviliste tiibadega pärast kookonist väljatulekut.","hints":[{"text":"Ma alustan kui roomik."},{"text":"Ma joon nektarit lilledest."},{"text":"I võib olla palju erinevaid värve."}],"options":[{"label":"Kärbes","isCorrect":false},{"label":"Liblikas","isCorrect":true},{"label":"Worm","isCorrect":false}],"additionalData":{"backgroundColor":"0xFFFFB74D","category":"bug","icon":"🦋"}},{"level":"6","type":"bug","question":"Mis ma olen? Ma laulan suvel öösel valjusti, aga sa näed mind harva.","hints":[{"text":"Ainult isased laulavad."},{"text":"Ma elan puudes."},{"text":"Minu heli on nagu kõrge \"zzzz\"."}],"options":[{"label":"Kriketid","isCorrect":false},{"label":"Tsikoda","isCorrect":true},{"label":"Tuletõrjekärbes","isCorrect":false}],"additionalData":{"backgroundColor":"0xFF4DB6AC","category":"bug","icon":"🎶"}},{"level":"7","type":"bug","question":"Mis ma olen? Ma rooman maas ja keerutan kleepuvat võrku, et oma õhtusööki kinni püüda.","hints":[{"text":"Mul on kaheksa jalga."},{"text":"Ma ei ole putukas."},{"text":"Minu võrk on tehtud siidist."}],"options":[{"label":"Ant","isCorrect":false},{"label":"Ämblik","isCorrect":true},{"label":"Roomik","isCorrect":false}],"additionalData":{"backgroundColor":"0xFFBA68C8","category":"bug","icon":"🕷️"}},{"level":"8","type":"bug","question":"Mis ma olen? Ma põlen öösel helendava helendusega.","hints":[{"text":"Ma olen väike ja lendan."},{"text":"Minu valgus aitab mul leida kaaslase."},{"text":"Ma elan rohumaal."}],"options":[{"label":"Tuletõrjekärbes","isCorrect":true},{"label":"Mesilane","isCorrect":false},{"label":"Koik","isCorrect":false}],"additionalData":{"backgroundColor":"0xFFFFCA28","category":"bug","icon":"🔦"}},{"level":"9","type":"bug","question":"Mis ma olen? Ma söön puitu ja võin kahjustada maju ja mööblit.","hints":[{"text":"Ma olen väike ja kahvatu."},{"text":"Ma elan maa-alustes kolooniates."},{"text":"Ma ei ole sipelgas, kuid inimesed peavad mind sageli sipelgaks."}],"options":[{"label":"Mardikas","isCorrect":false},{"label":"Termiit","isCorrect":true},{"label":"Ant","isCorrect":false}],"additionalData":{"backgroundColor":"0xFF6D4C41","category":"bug","icon":"🪵"}},{"level":"10","type":"bug","question":"Mis ma olen? Ma võin olla väga tüütu piknikul ja olen tuntud selle poolest, et mind tõmbab ligi valgus.","hints":[{"text":"Ma lendan siseruumides."},{"text":"Ma söön peaaegu kõike."},{"text":"Mul on kaks tiiba."}],"options":[{"label":"Kärbes","isCorrect":true},{"label":"Liblikas","isCorrect":false},{"label":"Rohutirts","isCorrect":false}],"additionalData":{"backgroundColor":"0xFF795548","category":"bug","icon":"🪰"}}],"animal":[{"level":"1","type":"animal","question":"Mis ma olen? Ma ütlen \"miau\" ja armastan lõngaga mängida.","hints":[{"text":"Mulle meeldib piima juua."},{"text":"Mul on pehme karvkate ja viskid."},{"text":"Mõnikord jälgin ma hiiri."}],"options":[{"label":"Koer","isCorrect":false},{"label":"Kass","isCorrect":true},{"label":"Linnu","isCorrect":false}],"additionalData":{"backgroundColor":"0xFFE91E63","category":"animal","icon":"🐱"}},{"level":"2","type":"animal","question":"Kes ma olen? Ma vingerdan oma sabaga ja haugun.","hints":[{"text":"Mulle meeldib tuua."},{"text":"Ma olen inimestele hea sõber."},{"text":"Mulle meeldib jalutama minna."}],"options":[{"label":"Duck","isCorrect":false},{"label":"Koer","isCorrect":true},{"label":"Lehm","isCorrect":false}],"additionalData":{"backgroundColor":"0xFF2196F3","category":"animal","icon":"🐶"}},{"level":"3","type":"animal","question":"Mis ma olen? Ma ütlen \"quack\" ja ujun vees.","hints":[{"text":"Mul on võrkjad jalad."},{"text":"Mulle meeldib leiba süüa."},{"text":"Mul on lai, lame nokk."}],"options":[{"label":"Duck","isCorrect":true},{"label":"Siga","isCorrect":false},{"label":"Hobune","isCorrect":false}],"additionalData":{"backgroundColor":"0xFF4CAF50","category":"animal","icon":"🦆"}},{"level":"4","type":"animal","question":"Kes ma olen? Ma annan sulle piima ja ütlen \"moo\".","hints":[{"text":"Ma elan talus."},{"text":"Ma söön rohtu."},{"text":"Ma olen suur."}],"options":[{"label":"Lehm","isCorrect":true},{"label":"Lammas","isCorrect":false},{"label":"Kana","isCorrect":false}],"additionalData":{"backgroundColor":"0xFFFFC107","category":"animal","icon":"🐮"}},{"level":"5","type":"animal","question":"Mis ma olen? Mul on pikk tüvi ja suured kõrvad.","hints":[{"text":"Ma elan Aafrikas ja Aasias."},{"text":"Ma söön taimi."},{"text":"Ma olen väga suur ja hall."}],"options":[{"label":"Elevant","isCorrect":true},{"label":"Lõvi","isCorrect":false},{"label":"Karu","isCorrect":false}],"additionalData":{"backgroundColor":"0xFF795548","category":"animal","icon":"🐘"}},{"level":"6","type":"animal","question":"Kes ma olen? Ma karjun ja mul on mannekeen.","hints":[{"text":"Ma olen džungli kuningas."},{"text":"Ma söön liha."},{"text":"Mul on teravad hambad."}],"options":[{"label":"Lõvi","isCorrect":true},{"label":"Tiiger","isCorrect":false},{"label":"Hunt","isCorrect":false}],"additionalData":{"backgroundColor":"0xFFFF9800","category":"animal","icon":"🦁"}},{"level":"7","type":"animal","question":"Mis ma olen? Ma hüppan ringi ja söön porgandeid.","hints":[{"text":"Mul on pikad kõrvad."},{"text":"Ma elan koopas."},{"text":"Mul on kohev saba."}],"options":[{"label":"Jänes","isCorrect":true},{"label":"Orav","isCorrect":false},{"label":"Hiir","isCorrect":false}],"additionalData":{"backgroundColor":"0xFF607D8B","category":"animal","icon":"🐰"}},{"level":"8","type":"animal","question":"Kes ma olen? Mul on mustad ja valged triibud.","hints":[{"text":"Ma näen välja nagu hobune."},{"text":"Ma elan Aafrikas."},{"text":"Minu triibud aitavad mind peita."}],"options":[{"label":"Seepra","isCorrect":true},{"label":"Kaelkirjak","isCorrect":false},{"label":"Gepard","isCorrect":false}],"additionalData":{"backgroundColor":"0xFF9E9E9E","category":"animal","icon":"🦓"}},{"level":"9","type":"animal","question":"Mis ma olen? Ma elan vees ja mul on palju jalgu.","hints":[{"text":"Ma pigistan oma küünistega."},{"text":"Ma olen punane, kui mind keedetakse."},{"text":"Ma käin külg ees."}],"options":[{"label":"Krabi","isCorrect":true},{"label":"Kala","isCorrect":false},{"label":"Meritäht","isCorrect":false}],"additionalData":{"backgroundColor":"0xFFF44336","category":"animal","icon":"🦞"}},{"level":"10","type":"animal","question":"Kes ma olen? Ma sirestan ja mul ei ole jalgu.","hints":[{"text":"Ma libisevad maas."},{"text":"Mõned meist on mürgised"},{"text":"Ma heidan oma nahka."}],"options":[{"label":"Worm","isCorrect":false},{"label":"Madu","isCorrect":true},{"label":"Roomik","isCorrect":false}],"additionalData":{"backgroundColor":"0xFF8BC34A","category":"animal","icon":"🐍"}}],"weather":[{"level":"1","type":"weather","question":"Mis ma olen? Ma langen taevast ja aitan lilledel kasvada.","hints":[{"text":"Ma tulen pilvedest."},{"text":"Sa pead mind tegema lörtsi."},{"text":"Põllumehed armastavad mind."}],"options":[{"label":"Päike ☀️","isCorrect":false},{"label":"Vihm 🌧️","isCorrect":true},{"label":"Tuul 💨","isCorrect":false}],"additionalData":{"backgroundColor":"0xFF87CEEB","category":"weather","icon":"🌧️"}},{"level":"2","type":"weather","question":"Mis ma olen? Ma olen suur ja kollane ja kuum taevas.","hints":[{"text":"Ma tulen päeva jooksul välja."},{"text":"Ma võin sind soojaks teha."},{"text":"Sa vajad päikeseprille, kui sa vaatad mind."}],"options":[{"label":"Kuu 🌙","isCorrect":false},{"label":"Päike ☀️","isCorrect":true},{"label":"Täht ⭐","isCorrect":false}],"additionalData":{"backgroundColor":"0xFFFFD700","category":"weather","icon":"☀️"}},{"level":"3","type":"weather","question":"Mis ma olen? Ma puhun kõvasti ja võin puud liigutada.","hints":[{"text":"Ma võin panna lehed lendama."},{"text":"Mõnikord ma vilistan."},{"text":"Sa võid koos minuga tuulelohega lennata."}],"options":[{"label":"Tuul 💨","isCorrect":true},{"label":"Vihm 🌧️","isCorrect":false},{"label":"Lumi ❄️","isCorrect":false}],"additionalData":{"backgroundColor":"0xFFA9A9A9","category":"weather","icon":"💨"}},{"level":"4","type":"weather","question":"Mis ma olen? Ma olen külm ja valge ja langen talvel taevast alla.","hints":[{"text":"Saate koos minuga teha lumememme."},{"text":"Ma sulan, kui läheb soojaks."},{"text":"Ma näen välja nagu pisikesed tähed."}],"options":[{"label":"Ave 🧊","isCorrect":false},{"label":"Lumi ❄️","isCorrect":true},{"label":"Udu 🌫️","isCorrect":false}],"additionalData":{"backgroundColor":"0xFFFFFFFF","category":"weather","icon":"❄️"}},{"level":"5","type":"weather","question":"Mis ma olen? Ma olen valge ja hõljun taevas.","hints":[{"text":"Mõnikord näen ma välja nagu loomad."},{"text":"Ma võin tuua vihma."},{"text":"Lennukid lendavad läbi minu."}],"options":[{"label":"Pilvede ☁️","isCorrect":true},{"label":"Täht ⭐","isCorrect":false},{"label":"Kuu 🌙","isCorrect":false}],"additionalData":{"backgroundColor":"0xFFF0F8FF","category":"weather","icon":"☁️"}},{"level":"6","type":"weather","question":"Mis ma olen? Ma olen torm, kus sajab palju vihma ja on kõva äike.","hints":[{"text":"Te võite koos minuga näha äikest."},{"text":"Ma võin olla hirmutav."},{"text":"Vahel juhtub suvel."}],"options":[{"label":"Lumetorm 🌨️","isCorrect":false},{"label":"Äikesetorm ⛈️","isCorrect":true},{"label":"Tolmukurat","isCorrect":false}],"additionalData":{"backgroundColor":"0xFF778899","category":"weather","icon":"⛈️"}},{"level":"7","type":"weather","question":"Mis ma olen? Ma olen tehtud jääst, aga ma langen sooja ilmaga.","hints":[{"text":"Ma olen väike ja ümmargune."},{"text":"Mõnikord on mul kukkudes valus."},{"text":"Ma ei ole lumi ega lörtsi."}],"options":[{"label":"Vihm 🌧️","isCorrect":false},{"label":"Ave 🧊","isCorrect":true},{"label":"Sleet","isCorrect":false}],"additionalData":{"backgroundColor":"0xFFB0E2FF","category":"weather","icon":"🧊"}},{"level":"8","type":"weather","question":"Mis ma olen? Ma olen värviline kaar, mis ilmub pärast vihma, kui päike läbi piilub.","hints":[{"text":"Mul on palju värve."},{"text":"Sa ei saa mind puudutada."},{"text":"Ma olen kaarekujuline."}],"options":[{"label":"Välk ⚡","isCorrect":false},{"label":"Vikerkaar 🌈","isCorrect":true},{"label":"Tornado 🌪️","isCorrect":false}],"additionalData":{"backgroundColor":"0xFFE6E6FA","category":"weather","icon":"🌈"}},{"level":"9","type":"weather","question":"Mis ma olen? Ma olen paks pilv maapinna lähedal, mis teeb raskesti nähtavaks.","hints":[{"text":"Asjad näevad hägused välja, kui ma olen lähedal."},{"text":"Lennujaamad suletakse mõnikord minu pärast."},{"text":"Ma olen nagu pilv maapinnal."}],"options":[{"label":"Udu 🌫️","isCorrect":true},{"label":"Udu","isCorrect":false},{"label":"Suitsu","isCorrect":false}],"additionalData":{"backgroundColor":"0xFFD3D3D3","category":"weather","icon":"🌫️"}},{"level":"10","type":"weather","question":"Mis ma olen? Ma olen nagu vihm, aga külmunud. Ma olen väiksem kui rahe ja sajan talvel.","hints":[{"text":"Ma olen segu vihmast ja lumest."},{"text":"Teed võivad olla libedad, kui ma kukkun."},{"text":"On külmem kui vihm, soojem kui lumi."}],"options":[{"label":"Lumi ❄️","isCorrect":false},{"label":"Sleet","isCorrect":true},{"label":"Ave 🧊","isCorrect":false}],"additionalData":{"backgroundColor":"0xFFAAAAAA","category":"weather","icon":"🌨️"}}]}